.gitignore
lrspline-1.15.1.dist-info/METADATA
lrspline-1.15.1.dist-info/WHEEL
lrspline-1.15.1.dist-info/entry_points.txt
lrspline-1.15.1.dist-info/licenses/COPYING
lrspline-1.15.1.dist-info/licenses/LICENSE
lrspline/__init__.py
lrspline/py.typed
lrspline/raw.cp311-win_amd64.pyd
lrspline/raw.cpp
lrspline/raw.pyi
lrspline/raw.pyx
lrspline-1.15.1.dist-info/RECORD
