Metadata-Version: 2.1
Name: lrspline
Version: 1.15.1
Summary: Python bindings for the LRSplines library
Author-Email: Eivind Fonn <eivind.fonn@sintef.no>
License: GPL-3-or-later
Requires-Python: <4.0,>=3.11
Requires-Dist: numpy<3.0,>=1.25
